[
    {
        "id": 1,
        "round": 1,
        "home_id": 1,
        "away_id": 6,
        "home_goals": null,
        "away_goals": null,
        "home_yellow": 0,
        "home_red": 0,
        "away_yellow": 0,
        "away_red": 0,
        "played": false,
        "notes": "",
        "status": "pendiente",
        "walkover_winner": null
    },
    {
        "id": 2,
        "round": 1,
        "home_id": 2,
        "away_id": 5,
        "home_goals": null,
        "away_goals": null,
        "home_yellow": 0,
        "home_red": 0,
        "away_yellow": 0,
        "away_red": 0,
        "played": false,
        "notes": "",
        "status": "pendiente",
        "walkover_winner": null
    },
    {
        "id": 3,
        "round": 1,
        "home_id": 3,
        "away_id": 4,
        "home_goals": null,
        "away_goals": null,
        "home_yellow": 0,
        "home_red": 0,
        "away_yellow": 0,
        "away_red": 0,
        "played": false,
        "notes": "",
        "status": "pendiente",
        "walkover_winner": null
    },
    {
        "id": 4,
        "round": 2,
        "home_id": 5,
        "away_id": 1,
        "home_goals": null,
        "away_goals": null,
        "home_yellow": 0,
        "home_red": 0,
        "away_yellow": 0,
        "away_red": 0,
        "played": false,
        "notes": "",
        "status": "pendiente",
        "walkover_winner": null
    },
    {
        "id": 5,
        "round": 2,
        "home_id": 4,
        "away_id": 6,
        "home_goals": null,
        "away_goals": null,
        "home_yellow": 0,
        "home_red": 0,
        "away_yellow": 0,
        "away_red": 0,
        "played": false,
        "notes": "",
        "status": "pendiente",
        "walkover_winner": null
    },
    {
        "id": 6,
        "round": 2,
        "home_id": 3,
        "away_id": 2,
        "home_goals": null,
        "away_goals": null,
        "home_yellow": 0,
        "home_red": 0,
        "away_yellow": 0,
        "away_red": 0,
        "played": false,
        "notes": "",
        "status": "pendiente",
        "walkover_winner": null
    },
    {
        "id": 7,
        "round": 3,
        "home_id": 1,
        "away_id": 4,
        "home_goals": null,
        "away_goals": null,
        "home_yellow": 0,
        "home_red": 0,
        "away_yellow": 0,
        "away_red": 0,
        "played": false,
        "notes": "",
        "status": "pendiente",
        "walkover_winner": null
    },
    {
        "id": 8,
        "round": 3,
        "home_id": 5,
        "away_id": 3,
        "home_goals": null,
        "away_goals": null,
        "home_yellow": 0,
        "home_red": 0,
        "away_yellow": 0,
        "away_red": 0,
        "played": false,
        "notes": "",
        "status": "pendiente",
        "walkover_winner": null
    },
    {
        "id": 9,
        "round": 3,
        "home_id": 6,
        "away_id": 2,
        "home_goals": null,
        "away_goals": null,
        "home_yellow": 0,
        "home_red": 0,
        "away_yellow": 0,
        "away_red": 0,
        "played": false,
        "notes": "",
        "status": "pendiente",
        "walkover_winner": null
    },
    {
        "id": 10,
        "round": 4,
        "home_id": 3,
        "away_id": 1,
        "home_goals": null,
        "away_goals": null,
        "home_yellow": 0,
        "home_red": 0,
        "away_yellow": 0,
        "away_red": 0,
        "played": false,
        "notes": "",
        "status": "pendiente",
        "walkover_winner": null
    },
    {
        "id": 11,
        "round": 4,
        "home_id": 2,
        "away_id": 4,
        "home_goals": null,
        "away_goals": null,
        "home_yellow": 0,
        "home_red": 0,
        "away_yellow": 0,
        "away_red": 0,
        "played": false,
        "notes": "",
        "status": "pendiente",
        "walkover_winner": null
    },
    {
        "id": 12,
        "round": 4,
        "home_id": 6,
        "away_id": 5,
        "home_goals": null,
        "away_goals": null,
        "home_yellow": 0,
        "home_red": 0,
        "away_yellow": 0,
        "away_red": 0,
        "played": false,
        "notes": "",
        "status": "pendiente",
        "walkover_winner": null
    },
    {
        "id": 13,
        "round": 5,
        "home_id": 1,
        "away_id": 2,
        "home_goals": null,
        "away_goals": null,
        "home_yellow": 0,
        "home_red": 0,
        "away_yellow": 0,
        "away_red": 0,
        "played": false,
        "notes": "",
        "status": "pendiente",
        "walkover_winner": null
    },
    {
        "id": 14,
        "round": 5,
        "home_id": 3,
        "away_id": 6,
        "home_goals": null,
        "away_goals": null,
        "home_yellow": 0,
        "home_red": 0,
        "away_yellow": 0,
        "away_red": 0,
        "played": false,
        "notes": "",
        "status": "pendiente",
        "walkover_winner": null
    },
    {
        "id": 15,
        "round": 5,
        "home_id": 4,
        "away_id": 5,
        "home_goals": null,
        "away_goals": null,
        "home_yellow": 0,
        "home_red": 0,
        "away_yellow": 0,
        "away_red": 0,
        "played": false,
        "notes": "",
        "status": "pendiente",
        "walkover_winner": null
    }
]